taggregator/__init__.py
taggregator/__main__.py
taggregator/config.py
taggregator/default_config.json
taggregator/printer.py
taggregator/tagg.py
taggregator/taggregator.py
taggregator-0.0.44.dist-info/LICENSE
taggregator-0.0.44.dist-info/METADATA
taggregator-0.0.44.dist-info/WHEEL
taggregator-0.0.44.dist-info/entry_points.txt
taggregator-0.0.44.dist-info/top_level.txt
taggregator-0.0.44.dist-info/RECORD
