Metadata-Version: 2.1
Name: taggregator
Version: 0.0.44
Summary: Find lines of source code you have tagged with custom categories
Home-page: https://github.com/jamtartley/taggregator
Author: Sam Hartley
Author-email: sam@jamtartley.com
License: UNKNOWN
Platform: UNKNOWN
Classifier: Programming Language :: Python :: 3
Classifier: License :: OSI Approved :: MIT License
Classifier: Operating System :: OS Independent
Requires-Python: >=3
